{
  "scan_summary": {
    "files_scanned": 26,
    "total_symbols": 51,
    "public_symbols": 50,
    "internal_symbols": 1,
    "errors": []
  },
  "confidence_distribution": {
    "high": 0,
    "medium": 4,
    "low": 46
  },
  "categories": {
    "other": 41,
    "component": 8,
    "utility": 1
  },
  "components": [
    {
      "id": "comp-supabase.functions.import-carelink-csv.index-findBlocks",
      "name": "findBlocks",
      "kind": "function",
      "file": "supabase/functions/import-carelink-csv/index.ts",
      "line": 13,
      "signature": "function findBlocks(lines: string[]): [number, number | null] | null",
      "module": "supabase.functions.import-carelink-csv.index",
      "confidence": {
        "score": 10,
        "tier": "low",
        "signals": {
          "has_docstring": false,
          "docstring_length": 0,
          "has_type_annotations": true,
          "path_matches_convention": false,
          "known_base_class": null,
          "name_follows_convention": false,
          "parent_validated": false
        }
      },
      "auto_category": "other",
      "auto_purpose": "",
      "depends_on": [],
      "internal": false,
      "methods": [],
      "docstring": null
    },
    {
      "id": "comp-supabase.functions.import-carelink-csv.index-isDataRow",
      "name": "isDataRow",
      "kind": "function",
      "file": "supabase/functions/import-carelink-csv/index.ts",
      "line": 23,
      "signature": "function isDataRow(line: string): boolean",
      "module": "supabase.functions.import-carelink-csv.index",
      "confidence": {
        "score": 10,
        "tier": "low",
        "signals": {
          "has_docstring": false,
          "docstring_length": 0,
          "has_type_annotations": true,
          "path_matches_convention": false,
          "known_base_class": null,
          "name_follows_convention": false,
          "parent_validated": false
        }
      },
      "auto_category": "other",
      "auto_purpose": "",
      "depends_on": [],
      "internal": false,
      "methods": [],
      "docstring": null
    },
    {
      "id": "comp-supabase.functions.import-carelink-csv.index-parseDateTime",
      "name": "parseDateTime",
      "kind": "function",
      "file": "supabase/functions/import-carelink-csv/index.ts",
      "line": 30,
      "signature": "function parseDateTime(dateStr: string, timeStr: string): Date | null",
      "module": "supabase.functions.import-carelink-csv.index",
      "confidence": {
        "score": 10,
        "tier": "low",
        "signals": {
          "has_docstring": false,
          "docstring_length": 0,
          "has_type_annotations": true,
          "path_matches_convention": false,
          "known_base_class": null,
          "name_follows_convention": false,
          "parent_validated": false
        }
      },
      "auto_category": "other",
      "auto_purpose": "",
      "depends_on": [],
      "internal": false,
      "methods": [],
      "docstring": null
    },
    {
      "id": "comp-supabase.functions.import-carelink-csv.index-parseCSV",
      "name": "parseCSV",
      "kind": "function",
      "file": "supabase/functions/import-carelink-csv/index.ts",
      "line": 42,
      "signature": "function parseCSV(header: string, dataLines: string[]): Record<string, string>[]",
      "module": "supabase.functions.import-carelink-csv.index",
      "confidence": {
        "score": 10,
        "tier": "low",
        "signals": {
          "has_docstring": false,
          "docstring_length": 0,
          "has_type_annotations": true,
          "path_matches_convention": false,
          "known_base_class": null,
          "name_follows_convention": false,
          "parent_validated": false
        }
      },
      "auto_category": "other",
      "auto_purpose": "",
      "depends_on": [],
      "internal": false,
      "methods": [],
      "docstring": null
    },
    {
      "id": "comp-supabase.functions.import-carelink-csv.index-processTreatments",
      "name": "processTreatments",
      "kind": "function",
      "file": "supabase/functions/import-carelink-csv/index.ts",
      "line": 54,
      "signature": "function processTreatments(lines: string[], headerIdx: number, dataEndIdx: number): object[]",
      "module": "supabase.functions.import-carelink-csv.index",
      "confidence": {
        "score": 10,
        "tier": "low",
        "signals": {
          "has_docstring": false,
          "docstring_length": 0,
          "has_type_annotations": true,
          "path_matches_convention": false,
          "known_base_class": null,
          "name_follows_convention": false,
          "parent_validated": false
        }
      },
      "auto_category": "other",
      "auto_purpose": "",
      "depends_on": [],
      "internal": false,
      "methods": [],
      "docstring": null
    },
    {
      "id": "comp-supabase.functions.import-carelink-csv.index-processEntries",
      "name": "processEntries",
      "kind": "function",
      "file": "supabase/functions/import-carelink-csv/index.ts",
      "line": 75,
      "signature": "function processEntries(lines: string[], headerIdx: number): object[]",
      "module": "supabase.functions.import-carelink-csv.index",
      "confidence": {
        "score": 10,
        "tier": "low",
        "signals": {
          "has_docstring": false,
          "docstring_length": 0,
          "has_type_annotations": true,
          "path_matches_convention": false,
          "known_base_class": null,
          "name_follows_convention": false,
          "parent_validated": false
        }
      },
      "auto_category": "other",
      "auto_purpose": "",
      "depends_on": [],
      "internal": false,
      "methods": [],
      "docstring": null
    },
    {
      "id": "comp-supabase.functions.import-carelink-csv.index-postToNightscout",
      "name": "postToNightscout",
      "kind": "function",
      "file": "supabase/functions/import-carelink-csv/index.ts",
      "line": 103,
      "signature": "function postToNightscout(\n  baseUrl: string,\n  apiSecretHash: string,\n  endpoint: \"entries\" | \"treatments\",\n  batch: object[]\n): Promise<{ status: number; ok: boolean }>",
      "module": "supabase.functions.import-carelink-csv.index",
      "confidence": {
        "score": 10,
        "tier": "low",
        "signals": {
          "has_docstring": false,
          "docstring_length": 0,
          "has_type_annotations": true,
          "path_matches_convention": false,
          "known_base_class": null,
          "name_follows_convention": false,
          "parent_validated": false
        }
      },
      "auto_category": "other",
      "auto_purpose": "",
      "depends_on": [],
      "internal": false,
      "methods": [],
      "docstring": null
    },
    {
      "id": "comp-docs.csv_upload.importar_ns_v2-module",
      "name": "importar_ns_v2",
      "kind": "module",
      "file": "docs/csv_upload/importar_ns_v2.py",
      "line": 1,
      "signature": "module importar_ns_v2",
      "module": "docs.csv_upload.importar_ns_v2",
      "confidence": {
        "score": 40,
        "tier": "medium",
        "signals": {
          "has_docstring": true,
          "docstring_length": 226,
          "has_type_annotations": false,
          "path_matches_convention": false,
          "known_base_class": null,
          "name_follows_convention": false,
          "parent_validated": false
        }
      },
      "auto_category": "other",
      "auto_purpose": "Importar datos de CareLink (CSV con dos bloques) a Nightscout.",
      "depends_on": [],
      "internal": false,
      "methods": [],
      "docstring": "Importar datos de CareLink (CSV con dos bloques) a Nightscout.\n\nDetecta autom\u00e1ticamente los dos bloques buscando las l\u00edneas de encabezado\nque empiezan con \"Index,Date,Time,...\". Bloque 1 \u2192 treatments, Bloque 2 \u2192 entries (sgv)."
    },
    {
      "id": "comp-docs.csv_upload.importar_ns_v2-log",
      "name": "log",
      "kind": "function",
      "file": "docs/csv_upload/importar_ns_v2.py",
      "line": 27,
      "signature": "def log(msg)",
      "module": "docs.csv_upload.importar_ns_v2",
      "confidence": {
        "score": 5,
        "tier": "low",
        "signals": {
          "has_docstring": false,
          "docstring_length": 0,
          "has_type_annotations": false,
          "path_matches_convention": false,
          "known_base_class": null,
          "name_follows_convention": true,
          "parent_validated": false
        }
      },
      "auto_category": "other",
      "auto_purpose": "",
      "depends_on": [],
      "internal": false,
      "methods": [],
      "docstring": null
    },
    {
      "id": "comp-docs.csv_upload.importar_ns_v2-encontrar_bloques",
      "name": "encontrar_bloques",
      "kind": "function",
      "file": "docs/csv_upload/importar_ns_v2.py",
      "line": 31,
      "signature": "def encontrar_bloques(lines)",
      "module": "docs.csv_upload.importar_ns_v2",
      "confidence": {
        "score": 45,
        "tier": "medium",
        "signals": {
          "has_docstring": true,
          "docstring_length": 153,
          "has_type_annotations": false,
          "path_matches_convention": false,
          "known_base_class": null,
          "name_follows_convention": true,
          "parent_validated": false
        }
      },
      "auto_category": "other",
      "auto_purpose": "Busca las dos l\u00edneas que son encabezado de datos (Index,Date,Time,.",
      "depends_on": [],
      "internal": false,
      "methods": [],
      "docstring": "Busca las dos l\u00edneas que son encabezado de datos (Index,Date,Time,...).\nDevuelve (idx_header_1, idx_header_2) en 0-based, o None si no hay exactamente 2."
    },
    {
      "id": "comp-docs.csv_upload.importar_ns_v2-upload_to_nightscout",
      "name": "upload_to_nightscout",
      "kind": "function",
      "file": "docs/csv_upload/importar_ns_v2.py",
      "line": 47,
      "signature": "def upload_to_nightscout(endpoint, data)",
      "module": "docs.csv_upload.importar_ns_v2",
      "confidence": {
        "score": 5,
        "tier": "low",
        "signals": {
          "has_docstring": false,
          "docstring_length": 0,
          "has_type_annotations": false,
          "path_matches_convention": false,
          "known_base_class": null,
          "name_follows_convention": true,
          "parent_validated": false
        }
      },
      "auto_category": "other",
      "auto_purpose": "",
      "depends_on": [],
      "internal": false,
      "methods": [],
      "docstring": null
    },
    {
      "id": "comp-docs.csv_upload.importar_ns_v2-parse_fecha_hora",
      "name": "parse_fecha_hora",
      "kind": "function",
      "file": "docs/csv_upload/importar_ns_v2.py",
      "line": 58,
      "signature": "def parse_fecha_hora(row)",
      "module": "docs.csv_upload.importar_ns_v2",
      "confidence": {
        "score": 5,
        "tier": "low",
        "signals": {
          "has_docstring": false,
          "docstring_length": 0,
          "has_type_annotations": false,
          "path_matches_convention": false,
          "known_base_class": null,
          "name_follows_convention": true,
          "parent_validated": false
        }
      },
      "auto_category": "other",
      "auto_purpose": "",
      "depends_on": [],
      "internal": false,
      "methods": [],
      "docstring": null
    },
    {
      "id": "comp-docs.csv_upload.importar_ns_v2-procesar_bloque_treatments",
      "name": "procesar_bloque_treatments",
      "kind": "function",
      "file": "docs/csv_upload/importar_ns_v2.py",
      "line": 75,
      "signature": "def procesar_bloque_treatments(lines, header_idx, data_end_idx)",
      "module": "docs.csv_upload.importar_ns_v2",
      "confidence": {
        "score": 45,
        "tier": "medium",
        "signals": {
          "has_docstring": true,
          "docstring_length": 108,
          "has_type_annotations": false,
          "path_matches_convention": false,
          "known_base_class": null,
          "name_follows_convention": true,
          "parent_validated": false
        }
      },
      "auto_category": "other",
      "auto_purpose": "Bloque 1: solo treatments (carbos).",
      "depends_on": [],
      "internal": false,
      "methods": [],
      "docstring": "Bloque 1: solo treatments (carbos). Solo se incluyen filas que parecen datos (excluye vac\u00edas y separadores)."
    },
    {
      "id": "comp-docs.csv_upload.importar_ns_v2-procesar_bloque_entries",
      "name": "procesar_bloque_entries",
      "kind": "function",
      "file": "docs/csv_upload/importar_ns_v2.py",
      "line": 100,
      "signature": "def procesar_bloque_entries(lines, header_idx)",
      "module": "docs.csv_upload.importar_ns_v2",
      "confidence": {
        "score": 45,
        "tier": "medium",
        "signals": {
          "has_docstring": true,
          "docstring_length": 101,
          "has_type_annotations": false,
          "path_matches_convention": false,
          "known_base_class": null,
          "name_follows_convention": true,
          "parent_validated": false
        }
      },
      "auto_category": "other",
      "auto_purpose": "Bloque 2: solo entries (Sensor Glucose).",
      "depends_on": [],
      "internal": false,
      "methods": [],
      "docstring": "Bloque 2: solo entries (Sensor Glucose). Solo filas que parecen datos; ignorar excepciones de sensor."
    },
    {
      "id": "comp-docs.csv_upload.importar_ns_v2-main",
      "name": "main",
      "kind": "function",
      "file": "docs/csv_upload/importar_ns_v2.py",
      "line": 132,
      "signature": "def main()",
      "module": "docs.csv_upload.importar_ns_v2",
      "confidence": {
        "score": 5,
        "tier": "low",
        "signals": {
          "has_docstring": false,
          "docstring_length": 0,
          "has_type_annotations": false,
          "path_matches_convention": false,
          "known_base_class": null,
          "name_follows_convention": true,
          "parent_validated": false
        }
      },
      "auto_category": "other",
      "auto_purpose": "",
      "depends_on": [],
      "internal": false,
      "methods": [],
      "docstring": null
    },
    {
      "id": "comp-frontend.src.App-App",
      "name": "App",
      "kind": "function",
      "file": "frontend/src/App.tsx",
      "line": 9,
      "signature": "function App()",
      "module": "frontend.src.App",
      "confidence": {
        "score": 0,
        "tier": "low",
        "signals": {
          "has_docstring": false,
          "docstring_length": 0,
          "has_type_annotations": false,
          "path_matches_convention": false,
          "known_base_class": null,
          "name_follows_convention": false,
          "parent_validated": false
        }
      },
      "auto_category": "other",
      "auto_purpose": "",
      "depends_on": [],
      "internal": false,
      "methods": [],
      "docstring": null
    },
    {
      "id": "comp-frontend.src.test-utils.mockSupabase-mockSupabase",
      "name": "mockSupabase",
      "kind": "constant",
      "file": "frontend/src/test-utils/mockSupabase.ts",
      "line": 2,
      "signature": "const mockSupabase",
      "module": "frontend.src.test-utils.mockSupabase",
      "confidence": {
        "score": 0,
        "tier": "low",
        "signals": {
          "has_docstring": false,
          "docstring_length": 0,
          "has_type_annotations": false,
          "path_matches_convention": false,
          "known_base_class": null,
          "name_follows_convention": false,
          "parent_validated": false
        }
      },
      "auto_category": "other",
      "auto_purpose": "",
      "depends_on": [],
      "internal": false,
      "methods": [],
      "docstring": null
    },
    {
      "id": "comp-frontend.src.components.MealCard-Props",
      "name": "Props",
      "kind": "type_alias",
      "file": "frontend/src/components/MealCard.tsx",
      "line": 3,
      "signature": "type Props",
      "module": "frontend.src.components.MealCard",
      "confidence": {
        "score": 20,
        "tier": "low",
        "signals": {
          "has_docstring": false,
          "docstring_length": 0,
          "has_type_annotations": false,
          "path_matches_convention": true,
          "known_base_class": null,
          "name_follows_convention": false,
          "parent_validated": false
        }
      },
      "auto_category": "component",
      "auto_purpose": "",
      "depends_on": [],
      "internal": false,
      "methods": [],
      "docstring": null
    },
    {
      "id": "comp-frontend.src.components.MealCard-MealCard",
      "name": "MealCard",
      "kind": "function",
      "file": "frontend/src/components/MealCard.tsx",
      "line": 6,
      "signature": "function MealCard({ meal }: Props)",
      "module": "frontend.src.components.MealCard",
      "confidence": {
        "score": 30,
        "tier": "low",
        "signals": {
          "has_docstring": false,
          "docstring_length": 0,
          "has_type_annotations": true,
          "path_matches_convention": true,
          "known_base_class": null,
          "name_follows_convention": false,
          "parent_validated": false
        }
      },
      "auto_category": "component",
      "auto_purpose": "",
      "depends_on": [],
      "internal": false,
      "methods": [],
      "docstring": null
    },
    {
      "id": "comp-frontend.src.components.BottomNav-BottomNav",
      "name": "BottomNav",
      "kind": "function",
      "file": "frontend/src/components/BottomNav.tsx",
      "line": 12,
      "signature": "function BottomNav()",
      "module": "frontend.src.components.BottomNav",
      "confidence": {
        "score": 20,
        "tier": "low",
        "signals": {
          "has_docstring": false,
          "docstring_length": 0,
          "has_type_annotations": false,
          "path_matches_convention": true,
          "known_base_class": null,
          "name_follows_convention": false,
          "parent_validated": false
        }
      },
      "auto_category": "component",
      "auto_purpose": "",
      "depends_on": [],
      "internal": false,
      "methods": [],
      "docstring": null
    },
    {
      "id": "comp-frontend.src.components.FilterBar-BitacoraFilter",
      "name": "BitacoraFilter",
      "kind": "type_alias",
      "file": "frontend/src/components/FilterBar.tsx",
      "line": 1,
      "signature": "type BitacoraFilter",
      "module": "frontend.src.components.FilterBar",
      "confidence": {
        "score": 20,
        "tier": "low",
        "signals": {
          "has_docstring": false,
          "docstring_length": 0,
          "has_type_annotations": false,
          "path_matches_convention": true,
          "known_base_class": null,
          "name_follows_convention": false,
          "parent_validated": false
        }
      },
      "auto_category": "component",
      "auto_purpose": "",
      "depends_on": [],
      "internal": false,
      "methods": [],
      "docstring": null
    },
    {
      "id": "comp-frontend.src.components.FilterBar-Props",
      "name": "Props",
      "kind": "type_alias",
      "file": "frontend/src/components/FilterBar.tsx",
      "line": 3,
      "signature": "type Props",
      "module": "frontend.src.components.FilterBar",
      "confidence": {
        "score": 20,
        "tier": "low",
        "signals": {
          "has_docstring": false,
          "docstring_length": 0,
          "has_type_annotations": false,
          "path_matches_convention": true,
          "known_base_class": null,
          "name_follows_convention": false,
          "parent_validated": false
        }
      },
      "auto_category": "component",
      "auto_purpose": "",
      "depends_on": [],
      "internal": false,
      "methods": [],
      "docstring": null
    },
    {
      "id": "comp-frontend.src.components.FilterBar-FilterBar",
      "name": "FilterBar",
      "kind": "function",
      "file": "frontend/src/components/FilterBar.tsx",
      "line": 20,
      "signature": "function FilterBar({\n  value,\n  onChange,\n  customStart = '',\n  customEnd = '',\n  onCustomStartChange,\n  onCustomEndChange,\n}: Props)",
      "module": "frontend.src.components.FilterBar",
      "confidence": {
        "score": 30,
        "tier": "low",
        "signals": {
          "has_docstring": false,
          "docstring_length": 0,
          "has_type_annotations": true,
          "path_matches_convention": true,
          "known_base_class": null,
          "name_follows_convention": false,
          "parent_validated": false
        }
      },
      "auto_category": "component",
      "auto_purpose": "",
      "depends_on": [],
      "internal": false,
      "methods": [],
      "docstring": null
    },
    {
      "id": "comp-frontend.src.components.CaptureMeal-Step",
      "name": "Step",
      "kind": "type_alias",
      "file": "frontend/src/components/CaptureMeal.tsx",
      "line": 10,
      "signature": "type Step",
      "module": "frontend.src.components.CaptureMeal",
      "confidence": {
        "score": 20,
        "tier": "low",
        "signals": {
          "has_docstring": false,
          "docstring_length": 0,
          "has_type_annotations": false,
          "path_matches_convention": true,
          "known_base_class": null,
          "name_follows_convention": false,
          "parent_validated": false
        }
      },
      "auto_category": "component",
      "auto_purpose": "",
      "depends_on": [],
      "internal": false,
      "methods": [],
      "docstring": null
    },
    {
      "id": "comp-frontend.src.components.CaptureMeal-CaptureMeal",
      "name": "CaptureMeal",
      "kind": "function",
      "file": "frontend/src/components/CaptureMeal.tsx",
      "line": 12,
      "signature": "function CaptureMeal()",
      "module": "frontend.src.components.CaptureMeal",
      "confidence": {
        "score": 20,
        "tier": "low",
        "signals": {
          "has_docstring": false,
          "docstring_length": 0,
          "has_type_annotations": false,
          "path_matches_convention": true,
          "known_base_class": null,
          "name_follows_convention": false,
          "parent_validated": false
        }
      },
      "auto_category": "component",
      "auto_purpose": "",
      "depends_on": [],
      "internal": false,
      "methods": [],
      "docstring": null
    },
    {
      "id": "comp-frontend.src.lib.supabase-supabase",
      "name": "supabase",
      "kind": "constant",
      "file": "frontend/src/lib/supabase.ts",
      "line": 10,
      "signature": "const supabase",
      "module": "frontend.src.lib.supabase",
      "confidence": {
        "score": 20,
        "tier": "low",
        "signals": {
          "has_docstring": false,
          "docstring_length": 0,
          "has_type_annotations": false,
          "path_matches_convention": true,
          "known_base_class": null,
          "name_follows_convention": false,
          "parent_validated": false
        }
      },
      "auto_category": "utility",
      "auto_purpose": "",
      "depends_on": [],
      "internal": false,
      "methods": [],
      "docstring": null
    },
    {
      "id": "comp-frontend.src.pages.PerfilPage-PerfilPage",
      "name": "PerfilPage",
      "kind": "function",
      "file": "frontend/src/pages/PerfilPage.tsx",
      "line": 6,
      "signature": "function PerfilPage()",
      "module": "frontend.src.pages.PerfilPage",
      "confidence": {
        "score": 0,
        "tier": "low",
        "signals": {
          "has_docstring": false,
          "docstring_length": 0,
          "has_type_annotations": false,
          "path_matches_convention": false,
          "known_base_class": null,
          "name_follows_convention": false,
          "parent_validated": false
        }
      },
      "auto_category": "other",
      "auto_purpose": "",
      "depends_on": [],
      "internal": false,
      "methods": [],
      "docstring": null
    },
    {
      "id": "comp-frontend.src.pages.CargaDatosPage-CargaDatosPage",
      "name": "CargaDatosPage",
      "kind": "function",
      "file": "frontend/src/pages/CargaDatosPage.tsx",
      "line": 5,
      "signature": "function CargaDatosPage()",
      "module": "frontend.src.pages.CargaDatosPage",
      "confidence": {
        "score": 0,
        "tier": "low",
        "signals": {
          "has_docstring": false,
          "docstring_length": 0,
          "has_type_annotations": false,
          "path_matches_convention": false,
          "known_base_class": null,
          "name_follows_convention": false,
          "parent_validated": false
        }
      },
      "auto_category": "other",
      "auto_purpose": "",
      "depends_on": [],
      "internal": false,
      "methods": [],
      "docstring": null
    },
    {
      "id": "comp-frontend.src.pages.HoyPage-HoyPage",
      "name": "HoyPage",
      "kind": "function",
      "file": "frontend/src/pages/HoyPage.tsx",
      "line": 7,
      "signature": "function HoyPage()",
      "module": "frontend.src.pages.HoyPage",
      "confidence": {
        "score": 0,
        "tier": "low",
        "signals": {
          "has_docstring": false,
          "docstring_length": 0,
          "has_type_annotations": false,
          "path_matches_convention": false,
          "known_base_class": null,
          "name_follows_convention": false,
          "parent_validated": false
        }
      },
      "auto_category": "other",
      "auto_purpose": "",
      "depends_on": [],
      "internal": false,
      "methods": [],
      "docstring": null
    },
    {
      "id": "comp-frontend.src.pages.LaboratorioPage-LaboratorioPage",
      "name": "LaboratorioPage",
      "kind": "function",
      "file": "frontend/src/pages/LaboratorioPage.tsx",
      "line": 6,
      "signature": "function LaboratorioPage()",
      "module": "frontend.src.pages.LaboratorioPage",
      "confidence": {
        "score": 0,
        "tier": "low",
        "signals": {
          "has_docstring": false,
          "docstring_length": 0,
          "has_type_annotations": false,
          "path_matches_convention": false,
          "known_base_class": null,
          "name_follows_convention": false,
          "parent_validated": false
        }
      },
      "auto_category": "other",
      "auto_purpose": "",
      "depends_on": [],
      "internal": false,
      "methods": [],
      "docstring": null
    },
    {
      "id": "comp-frontend.src.pages.BitacoraPage-getRangeForFilter",
      "name": "getRangeForFilter",
      "kind": "function",
      "file": "frontend/src/pages/BitacoraPage.tsx",
      "line": 8,
      "signature": "function getRangeForFilter(\n  filter: BitacoraFilter,\n  customStart: string,\n  customEnd: string\n): { start: Date; end: Date }",
      "module": "frontend.src.pages.BitacoraPage",
      "confidence": {
        "score": 10,
        "tier": "low",
        "signals": {
          "has_docstring": false,
          "docstring_length": 0,
          "has_type_annotations": true,
          "path_matches_convention": false,
          "known_base_class": null,
          "name_follows_convention": false,
          "parent_validated": false
        }
      },
      "auto_category": "other",
      "auto_purpose": "",
      "depends_on": [],
      "internal": false,
      "methods": [],
      "docstring": null
    },
    {
      "id": "comp-frontend.src.pages.BitacoraPage-BitacoraPage",
      "name": "BitacoraPage",
      "kind": "function",
      "file": "frontend/src/pages/BitacoraPage.tsx",
      "line": 45,
      "signature": "function BitacoraPage()",
      "module": "frontend.src.pages.BitacoraPage",
      "confidence": {
        "score": 0,
        "tier": "low",
        "signals": {
          "has_docstring": false,
          "docstring_length": 0,
          "has_type_annotations": false,
          "path_matches_convention": false,
          "known_base_class": null,
          "name_follows_convention": false,
          "parent_validated": false
        }
      },
      "auto_category": "other",
      "auto_purpose": "",
      "depends_on": [],
      "internal": false,
      "methods": [],
      "docstring": null
    },
    {
      "id": "comp-frontend.src.services.mealService-AnalyzeItem",
      "name": "AnalyzeItem",
      "kind": "type_alias",
      "file": "frontend/src/services/mealService.ts",
      "line": 7,
      "signature": "type AnalyzeItem",
      "module": "frontend.src.services.mealService",
      "confidence": {
        "score": 0,
        "tier": "low",
        "signals": {
          "has_docstring": false,
          "docstring_length": 0,
          "has_type_annotations": false,
          "path_matches_convention": false,
          "known_base_class": null,
          "name_follows_convention": false,
          "parent_validated": false
        }
      },
      "auto_category": "other",
      "auto_purpose": "",
      "depends_on": [],
      "internal": false,
      "methods": [],
      "docstring": null
    },
    {
      "id": "comp-frontend.src.services.mealService-AnalyzeResponse",
      "name": "AnalyzeResponse",
      "kind": "type_alias",
      "file": "frontend/src/services/mealService.ts",
      "line": 14,
      "signature": "type AnalyzeResponse",
      "module": "frontend.src.services.mealService",
      "confidence": {
        "score": 0,
        "tier": "low",
        "signals": {
          "has_docstring": false,
          "docstring_length": 0,
          "has_type_annotations": false,
          "path_matches_convention": false,
          "known_base_class": null,
          "name_follows_convention": false,
          "parent_validated": false
        }
      },
      "auto_category": "other",
      "auto_purpose": "",
      "depends_on": [],
      "internal": false,
      "methods": [],
      "docstring": null
    },
    {
      "id": "comp-frontend.src.services.mealService-MealRecord",
      "name": "MealRecord",
      "kind": "type_alias",
      "file": "frontend/src/services/mealService.ts",
      "line": 20,
      "signature": "type MealRecord",
      "module": "frontend.src.services.mealService",
      "confidence": {
        "score": 0,
        "tier": "low",
        "signals": {
          "has_docstring": false,
          "docstring_length": 0,
          "has_type_annotations": false,
          "path_matches_convention": false,
          "known_base_class": null,
          "name_follows_convention": false,
          "parent_validated": false
        }
      },
      "auto_category": "other",
      "auto_purpose": "",
      "depends_on": [],
      "internal": false,
      "methods": [],
      "docstring": null
    },
    {
      "id": "comp-frontend.src.services.mealService-validateImageFile",
      "name": "validateImageFile",
      "kind": "function",
      "file": "frontend/src/services/mealService.ts",
      "line": 28,
      "signature": "function validateImageFile(file: File): { ok: true } | { ok: false; message: string }",
      "module": "frontend.src.services.mealService",
      "confidence": {
        "score": 10,
        "tier": "low",
        "signals": {
          "has_docstring": false,
          "docstring_length": 0,
          "has_type_annotations": true,
          "path_matches_convention": false,
          "known_base_class": null,
          "name_follows_convention": false,
          "parent_validated": false
        }
      },
      "auto_category": "other",
      "auto_purpose": "",
      "depends_on": [],
      "internal": false,
      "methods": [],
      "docstring": null
    },
    {
      "id": "comp-frontend.src.services.mealService-uploadImage",
      "name": "uploadImage",
      "kind": "function",
      "file": "frontend/src/services/mealService.ts",
      "line": 39,
      "signature": "function uploadImage(file: File): Promise<{ url: string; path: string }>",
      "module": "frontend.src.services.mealService",
      "confidence": {
        "score": 10,
        "tier": "low",
        "signals": {
          "has_docstring": false,
          "docstring_length": 0,
          "has_type_annotations": true,
          "path_matches_convention": false,
          "known_base_class": null,
          "name_follows_convention": false,
          "parent_validated": false
        }
      },
      "auto_category": "other",
      "auto_purpose": "",
      "depends_on": [],
      "internal": false,
      "methods": [],
      "docstring": null
    },
    {
      "id": "comp-frontend.src.services.mealService-analyzeMeal",
      "name": "analyzeMeal",
      "kind": "function",
      "file": "frontend/src/services/mealService.ts",
      "line": 51,
      "signature": "function analyzeMeal(imageUrl: string): Promise<AnalyzeResponse>",
      "module": "frontend.src.services.mealService",
      "confidence": {
        "score": 10,
        "tier": "low",
        "signals": {
          "has_docstring": false,
          "docstring_length": 0,
          "has_type_annotations": true,
          "path_matches_convention": false,
          "known_base_class": null,
          "name_follows_convention": false,
          "parent_validated": false
        }
      },
      "auto_category": "other",
      "auto_purpose": "",
      "depends_on": [],
      "internal": false,
      "methods": [],
      "docstring": null
    },
    {
      "id": "comp-frontend.src.services.mealService-uploadAndAnalyze",
      "name": "uploadAndAnalyze",
      "kind": "function",
      "file": "frontend/src/services/mealService.ts",
      "line": 69,
      "signature": "function uploadAndAnalyze(file: File): Promise<{ response: AnalyzeResponse; imageUrl: string }>",
      "module": "frontend.src.services.mealService",
      "confidence": {
        "score": 10,
        "tier": "low",
        "signals": {
          "has_docstring": false,
          "docstring_length": 0,
          "has_type_annotations": true,
          "path_matches_convention": false,
          "known_base_class": null,
          "name_follows_convention": false,
          "parent_validated": false
        }
      },
      "auto_category": "other",
      "auto_purpose": "",
      "depends_on": [],
      "internal": false,
      "methods": [],
      "docstring": null
    },
    {
      "id": "comp-frontend.src.services.mealService-saveMeal",
      "name": "saveMeal",
      "kind": "function",
      "file": "frontend/src/services/mealService.ts",
      "line": 78,
      "signature": "function saveMeal(record: MealRecord): Promise<{ id: string }>",
      "module": "frontend.src.services.mealService",
      "confidence": {
        "score": 10,
        "tier": "low",
        "signals": {
          "has_docstring": false,
          "docstring_length": 0,
          "has_type_annotations": true,
          "path_matches_convention": false,
          "known_base_class": null,
          "name_follows_convention": false,
          "parent_validated": false
        }
      },
      "auto_category": "other",
      "auto_purpose": "",
      "depends_on": [],
      "internal": false,
      "methods": [],
      "docstring": null
    },
    {
      "id": "comp-frontend.src.services.mealService-MealEntry",
      "name": "MealEntry",
      "kind": "type_alias",
      "file": "frontend/src/services/mealService.ts",
      "line": 94,
      "signature": "type MealEntry",
      "module": "frontend.src.services.mealService",
      "confidence": {
        "score": 0,
        "tier": "low",
        "signals": {
          "has_docstring": false,
          "docstring_length": 0,
          "has_type_annotations": false,
          "path_matches_convention": false,
          "known_base_class": null,
          "name_follows_convention": false,
          "parent_validated": false
        }
      },
      "auto_category": "other",
      "auto_purpose": "",
      "depends_on": [],
      "internal": false,
      "methods": [],
      "docstring": null
    },
    {
      "id": "comp-frontend.src.services.mealService-getTodayMeals",
      "name": "getTodayMeals",
      "kind": "function",
      "file": "frontend/src/services/mealService.ts",
      "line": 103,
      "signature": "function getTodayMeals(): Promise<MealEntry[]>",
      "module": "frontend.src.services.mealService",
      "confidence": {
        "score": 10,
        "tier": "low",
        "signals": {
          "has_docstring": false,
          "docstring_length": 0,
          "has_type_annotations": true,
          "path_matches_convention": false,
          "known_base_class": null,
          "name_follows_convention": false,
          "parent_validated": false
        }
      },
      "auto_category": "other",
      "auto_purpose": "",
      "depends_on": [],
      "internal": false,
      "methods": [],
      "docstring": null
    },
    {
      "id": "comp-frontend.src.services.mealService-getMealsByRange",
      "name": "getMealsByRange",
      "kind": "function",
      "file": "frontend/src/services/mealService.ts",
      "line": 111,
      "signature": "function getMealsByRange(start: Date, end: Date): Promise<MealEntry[]>",
      "module": "frontend.src.services.mealService",
      "confidence": {
        "score": 10,
        "tier": "low",
        "signals": {
          "has_docstring": false,
          "docstring_length": 0,
          "has_type_annotations": true,
          "path_matches_convention": false,
          "known_base_class": null,
          "name_follows_convention": false,
          "parent_validated": false
        }
      },
      "auto_category": "other",
      "auto_purpose": "",
      "depends_on": [],
      "internal": false,
      "methods": [],
      "docstring": null
    },
    {
      "id": "comp-frontend.src.services.csvUploadService-ImportCsvResult",
      "name": "ImportCsvResult",
      "kind": "type_alias",
      "file": "frontend/src/services/csvUploadService.ts",
      "line": 3,
      "signature": "type ImportCsvResult",
      "module": "frontend.src.services.csvUploadService",
      "confidence": {
        "score": 0,
        "tier": "low",
        "signals": {
          "has_docstring": false,
          "docstring_length": 0,
          "has_type_annotations": false,
          "path_matches_convention": false,
          "known_base_class": null,
          "name_follows_convention": false,
          "parent_validated": false
        }
      },
      "auto_category": "other",
      "auto_purpose": "",
      "depends_on": [],
      "internal": false,
      "methods": [],
      "docstring": null
    },
    {
      "id": "comp-frontend.src.services.csvUploadService-uploadCareLinkCsv",
      "name": "uploadCareLinkCsv",
      "kind": "function",
      "file": "frontend/src/services/csvUploadService.ts",
      "line": 12,
      "signature": "function uploadCareLinkCsv(csvContent: string): Promise<ImportCsvResult>",
      "module": "frontend.src.services.csvUploadService",
      "confidence": {
        "score": 10,
        "tier": "low",
        "signals": {
          "has_docstring": false,
          "docstring_length": 0,
          "has_type_annotations": true,
          "path_matches_convention": false,
          "known_base_class": null,
          "name_follows_convention": false,
          "parent_validated": false
        }
      },
      "auto_category": "other",
      "auto_purpose": "",
      "depends_on": [],
      "internal": false,
      "methods": [],
      "docstring": null
    },
    {
      "id": "comp-frontend.src.services.catalogService-AddToCatalogPayload",
      "name": "AddToCatalogPayload",
      "kind": "type_alias",
      "file": "frontend/src/services/catalogService.ts",
      "line": 3,
      "signature": "type AddToCatalogPayload",
      "module": "frontend.src.services.catalogService",
      "confidence": {
        "score": 0,
        "tier": "low",
        "signals": {
          "has_docstring": false,
          "docstring_length": 0,
          "has_type_annotations": false,
          "path_matches_convention": false,
          "known_base_class": null,
          "name_follows_convention": false,
          "parent_validated": false
        }
      },
      "auto_category": "other",
      "auto_purpose": "",
      "depends_on": [],
      "internal": false,
      "methods": [],
      "docstring": null
    },
    {
      "id": "comp-frontend.src.services.catalogService-addToCatalog",
      "name": "addToCatalog",
      "kind": "function",
      "file": "frontend/src/services/catalogService.ts",
      "line": 11,
      "signature": "function addToCatalog(payload: AddToCatalogPayload): Promise<{ id: string }>",
      "module": "frontend.src.services.catalogService",
      "confidence": {
        "score": 10,
        "tier": "low",
        "signals": {
          "has_docstring": false,
          "docstring_length": 0,
          "has_type_annotations": true,
          "path_matches_convention": false,
          "known_base_class": null,
          "name_follows_convention": false,
          "parent_validated": false
        }
      },
      "auto_category": "other",
      "auto_purpose": "",
      "depends_on": [],
      "internal": false,
      "methods": [],
      "docstring": null
    },
    {
      "id": "comp-frontend.src.services.profileService-PumpProfile",
      "name": "PumpProfile",
      "kind": "type_alias",
      "file": "frontend/src/services/profileService.ts",
      "line": 3,
      "signature": "type PumpProfile",
      "module": "frontend.src.services.profileService",
      "confidence": {
        "score": 0,
        "tier": "low",
        "signals": {
          "has_docstring": false,
          "docstring_length": 0,
          "has_type_annotations": false,
          "path_matches_convention": false,
          "known_base_class": null,
          "name_follows_convention": false,
          "parent_validated": false
        }
      },
      "auto_category": "other",
      "auto_purpose": "",
      "depends_on": [],
      "internal": false,
      "methods": [],
      "docstring": null
    },
    {
      "id": "comp-frontend.src.services.profileService-getProfile",
      "name": "getProfile",
      "kind": "function",
      "file": "frontend/src/services/profileService.ts",
      "line": 11,
      "signature": "function getProfile(): Promise<PumpProfile | null>",
      "module": "frontend.src.services.profileService",
      "confidence": {
        "score": 10,
        "tier": "low",
        "signals": {
          "has_docstring": false,
          "docstring_length": 0,
          "has_type_annotations": true,
          "path_matches_convention": false,
          "known_base_class": null,
          "name_follows_convention": false,
          "parent_validated": false
        }
      },
      "auto_category": "other",
      "auto_purpose": "",
      "depends_on": [],
      "internal": false,
      "methods": [],
      "docstring": null
    },
    {
      "id": "comp-frontend.src.services.profileService-saveProfile",
      "name": "saveProfile",
      "kind": "function",
      "file": "frontend/src/services/profileService.ts",
      "line": 22,
      "signature": "function saveProfile(isf: number, ratio_ic: number): Promise<void>",
      "module": "frontend.src.services.profileService",
      "confidence": {
        "score": 10,
        "tier": "low",
        "signals": {
          "has_docstring": false,
          "docstring_length": 0,
          "has_type_annotations": true,
          "path_matches_convention": false,
          "known_base_class": null,
          "name_follows_convention": false,
          "parent_validated": false
        }
      },
      "auto_category": "other",
      "auto_purpose": "",
      "depends_on": [],
      "internal": false,
      "methods": [],
      "docstring": null
    }
  ],
  "module_groups": {
    "supabase/functions/import-carelink-csv/index.ts": [
      "comp-supabase.functions.import-carelink-csv.index-findBlocks",
      "comp-supabase.functions.import-carelink-csv.index-isDataRow",
      "comp-supabase.functions.import-carelink-csv.index-parseDateTime",
      "comp-supabase.functions.import-carelink-csv.index-parseCSV",
      "comp-supabase.functions.import-carelink-csv.index-processTreatments",
      "comp-supabase.functions.import-carelink-csv.index-processEntries",
      "comp-supabase.functions.import-carelink-csv.index-postToNightscout"
    ],
    "docs/csv_upload/importar_ns_v2.py": [
      "comp-docs.csv_upload.importar_ns_v2-module",
      "comp-docs.csv_upload.importar_ns_v2-log",
      "comp-docs.csv_upload.importar_ns_v2-encontrar_bloques",
      "comp-docs.csv_upload.importar_ns_v2-upload_to_nightscout",
      "comp-docs.csv_upload.importar_ns_v2-parse_fecha_hora",
      "comp-docs.csv_upload.importar_ns_v2-procesar_bloque_treatments",
      "comp-docs.csv_upload.importar_ns_v2-procesar_bloque_entries",
      "comp-docs.csv_upload.importar_ns_v2-main"
    ],
    "frontend/src/App.tsx": [
      "comp-frontend.src.App-App"
    ],
    "frontend/src/test-utils/mockSupabase.ts": [
      "comp-frontend.src.test-utils.mockSupabase-mockSupabase"
    ],
    "frontend/src/components/MealCard.tsx": [
      "comp-frontend.src.components.MealCard-Props",
      "comp-frontend.src.components.MealCard-MealCard"
    ],
    "frontend/src/components/BottomNav.tsx": [
      "comp-frontend.src.components.BottomNav-BottomNav"
    ],
    "frontend/src/components/FilterBar.tsx": [
      "comp-frontend.src.components.FilterBar-BitacoraFilter",
      "comp-frontend.src.components.FilterBar-Props",
      "comp-frontend.src.components.FilterBar-FilterBar"
    ],
    "frontend/src/components/CaptureMeal.tsx": [
      "comp-frontend.src.components.CaptureMeal-Step",
      "comp-frontend.src.components.CaptureMeal-CaptureMeal"
    ],
    "frontend/src/lib/supabase.ts": [
      "comp-frontend.src.lib.supabase-supabase"
    ],
    "frontend/src/pages/PerfilPage.tsx": [
      "comp-frontend.src.pages.PerfilPage-PerfilPage"
    ],
    "frontend/src/pages/CargaDatosPage.tsx": [
      "comp-frontend.src.pages.CargaDatosPage-CargaDatosPage"
    ],
    "frontend/src/pages/HoyPage.tsx": [
      "comp-frontend.src.pages.HoyPage-HoyPage"
    ],
    "frontend/src/pages/LaboratorioPage.tsx": [
      "comp-frontend.src.pages.LaboratorioPage-LaboratorioPage"
    ],
    "frontend/src/pages/BitacoraPage.tsx": [
      "comp-frontend.src.pages.BitacoraPage-getRangeForFilter",
      "comp-frontend.src.pages.BitacoraPage-BitacoraPage"
    ],
    "frontend/src/services/mealService.ts": [
      "comp-frontend.src.services.mealService-AnalyzeItem",
      "comp-frontend.src.services.mealService-AnalyzeResponse",
      "comp-frontend.src.services.mealService-MealRecord",
      "comp-frontend.src.services.mealService-validateImageFile",
      "comp-frontend.src.services.mealService-uploadImage",
      "comp-frontend.src.services.mealService-analyzeMeal",
      "comp-frontend.src.services.mealService-uploadAndAnalyze",
      "comp-frontend.src.services.mealService-saveMeal",
      "comp-frontend.src.services.mealService-MealEntry",
      "comp-frontend.src.services.mealService-getTodayMeals",
      "comp-frontend.src.services.mealService-getMealsByRange"
    ],
    "frontend/src/services/csvUploadService.ts": [
      "comp-frontend.src.services.csvUploadService-ImportCsvResult",
      "comp-frontend.src.services.csvUploadService-uploadCareLinkCsv"
    ],
    "frontend/src/services/catalogService.ts": [
      "comp-frontend.src.services.catalogService-AddToCatalogPayload",
      "comp-frontend.src.services.catalogService-addToCatalog"
    ],
    "frontend/src/services/profileService.ts": [
      "comp-frontend.src.services.profileService-PumpProfile",
      "comp-frontend.src.services.profileService-getProfile",
      "comp-frontend.src.services.profileService-saveProfile"
    ]
  }
}